snowmachine/__init__.py
snowmachine/__main__.py
snowmachine-2.0.2.dist-info/METADATA
snowmachine-2.0.2.dist-info/WHEEL
snowmachine-2.0.2.dist-info/entry_points.txt
snowmachine-2.0.2.dist-info/licenses/LICENSE.txt
snowmachine-2.0.2.dist-info/RECORD
