Metadata-Version: 2.4
Name: snowmachine
Version: 2.0.2
Summary: A python script that will make your terminal snow.
Project-URL: Homepage, https://github.com/sontek/snowmachine
Author-email: John Anderson <sontek@gmail.com>
License-File: LICENSE.txt
Classifier: License :: OSI Approved :: BSD License
Classifier: Operating System :: OS Independent
Classifier: Programming Language :: Python :: 3
Requires-Python: >=3.8
Requires-Dist: click
Requires-Dist: colorama
